odoo/addons/sale_stock_reconcile_valuation_kit/README.rst
odoo/addons/sale_stock_reconcile_valuation_kit/__init__.py
odoo/addons/sale_stock_reconcile_valuation_kit/__manifest__.py
odoo/addons/sale_stock_reconcile_valuation_kit/i18n/es.po
odoo/addons/sale_stock_reconcile_valuation_kit/i18n/it.po
odoo/addons/sale_stock_reconcile_valuation_kit/i18n/sale_stock_reconcile_valuation_kit.pot
odoo/addons/sale_stock_reconcile_valuation_kit/models/__init__.py
odoo/addons/sale_stock_reconcile_valuation_kit/models/account_move.py
odoo/addons/sale_stock_reconcile_valuation_kit/readme/CONTRIBUTORS.rst
odoo/addons/sale_stock_reconcile_valuation_kit/readme/DESCRIPTION.rst
odoo/addons/sale_stock_reconcile_valuation_kit/static/description/icon.png
odoo/addons/sale_stock_reconcile_valuation_kit/static/description/index.html
odoo/addons/sale_stock_reconcile_valuation_kit/test/__init__.py
odoo/addons/sale_stock_reconcile_valuation_kit/test/test_sale_stock_reconcile_valuation_kit.py
odoo14_addon_sale_stock_reconcile_valuation_kit-14.0.1.0.1.dev7.dist-info/METADATA
odoo14_addon_sale_stock_reconcile_valuation_kit-14.0.1.0.1.dev7.dist-info/WHEEL
odoo14_addon_sale_stock_reconcile_valuation_kit-14.0.1.0.1.dev7.dist-info/top_level.txt
odoo14_addon_sale_stock_reconcile_valuation_kit-14.0.1.0.1.dev7.dist-info/RECORD
